boring_math/recursive_functions/__init__.py
boring_math/recursive_functions/ackermann.py
boring_math/recursive_functions/fibonacci.py
boring_math/recursive_functions/py.typed
boring_math/recursive_functions/cli/__init__.py
boring_math/recursive_functions/cli/ackermann_cli.py
boring_math/recursive_functions/cli/fibonacci_cli.py
boring_math/recursive_functions/cli/py.typed
boring_math_recursive_functions-1.0.0.dist-info/entry_points.txt
boring_math_recursive_functions-1.0.0.dist-info/licenses/LICENSE
boring_math_recursive_functions-1.0.0.dist-info/WHEEL
boring_math_recursive_functions-1.0.0.dist-info/METADATA
boring_math_recursive_functions-1.0.0.dist-info/RECORD
