Metadata-Version: 2.4
Name: boring-math-recursive-functions
Version: 1.0.0
Summary: Recursive Functions Package
Keywords: ackermann,fibonacci,recursive,recursive functions
Author-email: "Geoffrey R. Scheller" <geoffrey@scheller.com>
Requires-Python: >=3.13
Classifier: Development Status :: 3 - Alpha
Classifier: Framework :: Pytest
Classifier: Intended Audience :: Education
Classifier: License :: OSI Approved :: Apache Software License
Classifier: Operating System :: OS Independent
Classifier: Programming Language :: Python :: 3.13
Classifier: Typing :: Typed
License-File: LICENSE
Requires-Dist: pythonic-fp-iterables>=5.1.2
Requires-Dist: pytest>=8.4.1 ; extra == "test"
Project-URL: Changelog, https://github.com/grscheller/boring-math-recursive-functions/blob/main/CHANGELOG.md
Project-URL: Documentation, https://grscheller.github.io/boring-math/recursive-functions/development/build/html
Project-URL: Homepage, https://grscheller.github.io/boring-math/homepage/build/html
Project-URL: Source, https://github.com/grscheller/boring-math-recursive-functions
Provides-Extra: test
